sm_env_read/__init__.py
sm_env_read/main.py
sm_env_read-1.1.0.dist-info/METADATA
sm_env_read-1.1.0.dist-info/WHEEL
sm_env_read-1.1.0.dist-info/top_level.txt
sm_env_read-1.1.0.dist-info/RECORD
