Metadata-Version: 2.4
Name: sm_env_read
Version: 1.1.0
Summary: read env secrets from aws secrets manager
Author: Deepak M S
Author-email: deepakcoder80@gmail.com
Requires-Dist: boto3
Dynamic: author
Dynamic: author-email
Dynamic: description
Dynamic: description-content-type
Dynamic: requires-dist
Dynamic: summary
